README.md
setup.cfg
setup.py
distri_package/Binomialdistribution.py
distri_package/Gaussiandistribution.py
distri_package/Generaldistribution.py
distri_package/__init__.py
distri_package.egg-info/PKG-INFO
distri_package.egg-info/SOURCES.txt
distri_package.egg-info/dependency_links.txt
distri_package.egg-info/not-zip-safe
distri_package.egg-info/top_level.txt